{"t": "Title 14 Housing Authority", "p": "/us/nsn/tmchippewa/council/code/14", "et": "container", "dj": "/us/nsn/tmchippewa/council/code/index.json", "fh": "/us/nsn/tmchippewa/council/code/14/index.full.html", "sc": "Title 14", "sp": "library|Turtle Mountain Band of Chippewa Indians Tribal Code|14", "c": [{"t": "Chapter 14.01 Declaration of Need", "p": "/us/nsn/tmchippewa/council/code/14.01", "et": "container", "sc": "Chapter 14.01", "sp": "library|Turtle Mountain Band of Chippewa Indians Tribal Code|14|14.01", "c": [{"t": "14.01.010 Declaration of Need", "p": "/us/nsn/tmchippewa/council/code/14.01.010", "et": "section", "sc": "Section 14.01.010", "sp": "library|Turtle Mountain Band of Chippewa Indians Tribal Code|14|14.01|14.01.010"}, {"t": "14.01.020 Purposes", "p": "/us/nsn/tmchippewa/council/code/14.01.020", "et": "section", "sc": "Section 14.01.020", "sp": "library|Turtle Mountain Band of Chippewa Indians Tribal Code|14|14.01|14.01.020", "c": [{"t": "(a)", "p": "/us/nsn/tmchippewa/council/code/14.01.020#(a)", "et": "para", "sc": "Section 14.01.020(a)", "x": "Remedying on the Reservation unsafe and unsanitary housing conditions that "}, {"t": "(b)", "p": "/us/nsn/tmchippewa/council/code/14.01.020#(b)", "et": "para", "sc": "Section 14.01.020(b)", "x": "Alleviating the acute shortage of decent, safe and sanitary dwellings for f"}, {"t": "(c)", "p": "/us/nsn/tmchippewa/council/code/14.01.020#(c)", "et": "para", "sc": "Section 14.01.020(c)", "x": "Providing employment opportunities on the Reservation through the construct"}]}]}, {"t": "Chapter 14.02 Definitions", "p": "/us/nsn/tmchippewa/council/code/14.02", "et": "container", "sc": "Chapter 14.02", "sp": "library|Turtle Mountain Band of Chippewa Indians Tribal Code|14|14.02", "c": [{"t": "14.02.010 Definitions", "p": "/us/nsn/tmchippewa/council/code/14.02.010", "et": "section", "sc": "Section 14.02.010", "sp": "library|Turtle Mountain Band of Chippewa Indians Tribal Code|14|14.02|14.02.010", "c": [{"t": "(a)", "p": "/us/nsn/tmchippewa/council/code/14.02.010#(a)", "et": "para", "sc": "Section 14.02.010(a)", "x": "\"Board\" means the Board of Commissioners of the Authority."}, {"t": "(b)", "p": "/us/nsn/tmchippewa/council/code/14.02.010#(b)", "et": "para", "sc": "Section 14.02.010(b)", "x": "\"Council\" means the Turtle Mountain Chippewa Tribal Council."}, {"t": "(c)", "p": "/us/nsn/tmchippewa/council/code/14.02.010#(c)", "et": "para", "sc": "Section 14.02.010(c)", "x": "\"Federal Government\" includes the United States of America, the Public Hous"}, {"t": "(d)", "p": "/us/nsn/tmchippewa/council/code/14.02.010#(d)", "et": "para", "sc": "Section 14.02.010(d)", "x": "\"Area of Concern\" means any area where dwellings predominate which by reaso"}, {"t": "(e)", "p": "/us/nsn/tmchippewa/council/code/14.02.010#(e)", "et": "para", "sc": "Section 14.02.010(e)", "c": [{"t": "(1)", "p": "/us/nsn/tmchippewa/council/code/14.02.010#(e)(1)", "et": "para", "sc": "Section 14.02.010(e)(1)", "x": "to demolish, clear, or remove buildings from any area of concern,"}, {"t": "(2)", "p": "/us/nsn/tmchippewa/council/code/14.02.010#(e)(2)", "et": "para", "sc": "Section 14.02.010(e)(2)", "x": "to provide decent, safe and sanitary dwellings, apartments, or other living"}, {"t": "(3)", "p": "/us/nsn/tmchippewa/council/code/14.02.010#(e)(3)", "et": "para", "sc": "Section 14.02.010(e)(3)", "x": "to accomplish a combination of the foregoing."}], "x": "\"Housing Project\" or \"project\" means any work or undertaking:"}, {"t": "(f)", "p": "/us/nsn/tmchippewa/council/code/14.02.010#(f)", "et": "para", "sc": "Section 14.02.010(f)", "x": "\"Persons of low income\" means persons or families who lack the amount of in"}, {"t": "(g)", "p": "/us/nsn/tmchippewa/council/code/14.02.010#(g)", "et": "para", "sc": "Section 14.02.010(g)", "x": "\"Bonds\" means any bonds, notes, interim certificates, debentures, or other "}, {"t": "(h)", "p": "/us/nsn/tmchippewa/council/code/14.02.010#(h)", "et": "para", "sc": "Section 14.02.010(h)", "x": "\"Obligee\" includes any bondholder agent or trustee for any bondholder or le"}, {"t": "(i)", "p": "/us/nsn/tmchippewa/council/code/14.02.010#(i)", "et": "para", "sc": "Section 14.02.010(i)", "x": "\"Home Buyer\" means a person who has executed a lease-purchase agreement wit"}]}]}, {"t": "Chapter 14.03 Organization", "p": "/us/nsn/tmchippewa/council/code/14.03", "et": "container", "sc": "Chapter 14.03", "sp": "library|Turtle Mountain Band of Chippewa Indians Tribal Code|14|14.03", "c": [{"t": "14.03.010 Appointment of Board Members", "p": "/us/nsn/tmchippewa/council/code/14.03.010", "et": "section", "sc": "Section 14.03.010", "sp": "library|Turtle Mountain Band of Chippewa Indians Tribal Code|14|14.03|14.03.010"}, {"t": "14.03.020 Term of Office", "p": "/us/nsn/tmchippewa/council/code/14.03.020", "et": "section", "sc": "Section 14.03.020", "sp": "library|Turtle Mountain Band of Chippewa Indians Tribal Code|14|14.03|14.03.020"}, {"t": "14.03.030 Officers", "p": "/us/nsn/tmchippewa/council/code/14.03.030", "et": "section", "sc": "Section 14.03.030", "sp": "library|Turtle Mountain Band of Chippewa Indians Tribal Code|14|14.03|14.03.030"}, {"t": "14.03.040 Removal", "p": "/us/nsn/tmchippewa/council/code/14.03.040", "et": "section", "sc": "Section 14.03.040", "sp": "library|Turtle Mountain Band of Chippewa Indians Tribal Code|14|14.03|14.03.040"}, {"t": "14.03.050 Compensation", "p": "/us/nsn/tmchippewa/council/code/14.03.050", "et": "section", "sc": "Section 14.03.050", "sp": "library|Turtle Mountain Band of Chippewa Indians Tribal Code|14|14.03|14.03.050"}, {"t": "14.03.060 Meetings", "p": "/us/nsn/tmchippewa/council/code/14.03.060", "et": "section", "sc": "Section 14.03.060", "sp": "library|Turtle Mountain Band of Chippewa Indians Tribal Code|14|14.03|14.03.060"}, {"t": "14.03.070 Minutes of Meetings", "p": "/us/nsn/tmchippewa/council/code/14.03.070", "et": "section", "sc": "Section 14.03.070", "sp": "library|Turtle Mountain Band of Chippewa Indians Tribal Code|14|14.03|14.03.070"}, {"t": "14.03.080 Financial Records", "p": "/us/nsn/tmchippewa/council/code/14.03.080", "et": "section", "sc": "Section 14.03.080", "sp": "library|Turtle Mountain Band of Chippewa Indians Tribal Code|14|14.03|14.03.080"}]}, {"t": "Chapter 14.04 Powers", "p": "/us/nsn/tmchippewa/council/code/14.04", "et": "container", "sc": "Chapter 14.04", "sp": "library|Turtle Mountain Band of Chippewa Indians Tribal Code|14|14.04", "c": [{"t": "14.04.010 Authority", "p": "/us/nsn/tmchippewa/council/code/14.04.010", "et": "section", "sc": "Section 14.04.010", "sp": "library|Turtle Mountain Band of Chippewa Indians Tribal Code|14|14.04|14.04.010"}, {"t": "14.04.020 Corporate Seal", "p": "/us/nsn/tmchippewa/council/code/14.04.020", "et": "section", "sc": "Section 14.04.020", "sp": "library|Turtle Mountain Band of Chippewa Indians Tribal Code|14|14.04|14.04.020"}, {"t": "14.04.030 Contracts and Agreements", "p": "/us/nsn/tmchippewa/council/code/14.04.030", "et": "section", "sc": "Section 14.04.030", "sp": "library|Turtle Mountain Band of Chippewa Indians Tribal Code|14|14.04|14.04.030"}, {"t": "14.04.040 Wages", "p": "/us/nsn/tmchippewa/council/code/14.04.040", "et": "section", "sc": "Section 14.04.040", "sp": "library|Turtle Mountain Band of Chippewa Indians Tribal Code|14|14.04|14.04.040"}, {"t": "14.04.050 Conveyance to Federal Government", "p": "/us/nsn/tmchippewa/council/code/14.04.050", "et": "section", "sc": "Section 14.04.050", "sp": "library|Turtle Mountain Band of Chippewa Indians Tribal Code|14|14.04|14.04.050"}, {"t": "14.04.060 Negotiate Leases", "p": "/us/nsn/tmchippewa/council/code/14.04.060", "et": "section", "sc": "Section 14.04.060", "sp": "library|Turtle Mountain Band of Chippewa Indians Tribal Code|14|14.04|14.04.060", "c": [{"t": "(a)", "p": "/us/nsn/tmchippewa/council/code/14.04.060#(a)", "et": "para", "sc": "Section 14.04.060(a)", "x": "To lease property from the tribe and others for such periods as are authori"}, {"t": "(b)", "p": "/us/nsn/tmchippewa/council/code/14.04.060#(b)", "et": "para", "sc": "Section 14.04.060(b)", "c": [{"t": "(1)", "p": "/us/nsn/tmchippewa/council/code/14.04.060#(b)(1)", "et": "para", "sc": "Section 14.04.060(b)(1)", "x": "establishing lower than average rentals for especially needy families; and"}, {"t": "(2)", "p": "/us/nsn/tmchippewa/council/code/14.04.060#(b)(2)", "et": "para", "sc": "Section 14.04.060(b)(2)", "x": "by establishing income limits for admission and continued occupancy by low "}], "x": "To lease or rent any dwellings, accommodations, lands, buildings, or facili"}]}, {"t": "14.04.070 Borrow Money", "p": "/us/nsn/tmchippewa/council/code/14.04.070", "et": "section", "sc": "Section 14.04.070", "sp": "library|Turtle Mountain Band of Chippewa Indians Tribal Code|14|14.04|14.04.070"}, {"t": "14.04.080 Mortgage Property", "p": "/us/nsn/tmchippewa/council/code/14.04.080", "et": "section", "sc": "Section 14.04.080", "sp": "library|Turtle Mountain Band of Chippewa Indians Tribal Code|14|14.04|14.04.080"}, {"t": "14.04.090 Acquire Land", "p": "/us/nsn/tmchippewa/council/code/14.04.090", "et": "section", "sc": "Section 14.04.090", "sp": "library|Turtle Mountain Band of Chippewa Indians Tribal Code|14|14.04|14.04.090"}, {"t": "14.04.100 Conduct Research", "p": "/us/nsn/tmchippewa/council/code/14.04.100", "et": "section", "sc": "Section 14.04.100", "sp": "library|Turtle Mountain Band of Chippewa Indians Tribal Code|14|14.04|14.04.100"}, {"t": "14.04.110 Investment of Funds", "p": "/us/nsn/tmchippewa/council/code/14.04.110", "et": "section", "sc": "Section 14.04.110", "sp": "library|Turtle Mountain Band of Chippewa Indians Tribal Code|14|14.04|14.04.110", "c": [{"t": "(a)", "p": "/us/nsn/tmchippewa/council/code/14.04.110#(a)", "et": "para", "sc": "Section 14.04.110(a)", "x": "To purchase insurance in any stock or mutual company for any property or ag"}, {"t": "(b)", "p": "/us/nsn/tmchippewa/council/code/14.04.110#(b)", "et": "para", "sc": "Section 14.04.110(b)", "x": "To invest such funds as are not required for immediate disbursement."}]}, {"t": "14.04.120 Banking of Funds", "p": "/us/nsn/tmchippewa/council/code/14.04.120", "et": "section", "sc": "Section 14.04.120", "sp": "library|Turtle Mountain Band of Chippewa Indians Tribal Code|14|14.04|14.04.120"}, {"t": "14.04.130 Staff", "p": "/us/nsn/tmchippewa/council/code/14.04.130", "et": "section", "sc": "Section 14.04.130", "sp": "library|Turtle Mountain Band of Chippewa Indians Tribal Code|14|14.04|14.04.130"}, {"t": "14.04.140 Income Limits", "p": "/us/nsn/tmchippewa/council/code/14.04.140", "et": "section", "sc": "Section 14.04.140", "sp": "library|Turtle Mountain Band of Chippewa Indians Tribal Code|14|14.04|14.04.140"}, {"t": "14.04.150 Eviction", "p": "/us/nsn/tmchippewa/council/code/14.04.150", "et": "section", "sc": "Section 14.04.150", "sp": "library|Turtle Mountain Band of Chippewa Indians Tribal Code|14|14.04|14.04.150"}, {"t": "14.04.160 Other", "p": "/us/nsn/tmchippewa/council/code/14.04.160", "et": "section", "sc": "Section 14.04.160", "sp": "library|Turtle Mountain Band of Chippewa Indians Tribal Code|14|14.04|14.04.160"}]}, {"t": "Chapter 14.05 Bonds", "p": "/us/nsn/tmchippewa/council/code/14.05", "et": "container", "sc": "Chapter 14.05", "sp": "library|Turtle Mountain Band of Chippewa Indians Tribal Code|14|14.05", "c": [{"t": "14.05.010 Issuance of Bonds", "p": "/us/nsn/tmchippewa/council/code/14.05.010", "et": "section", "sc": "Section 14.05.010", "sp": "library|Turtle Mountain Band of Chippewa Indians Tribal Code|14|14.05|14.05.010", "c": [{"t": "(a)", "p": "/us/nsn/tmchippewa/council/code/14.05.010#(a)", "et": "para", "sc": "Section 14.05.010(a)", "x": "Exclusively from the income and revenues of the project financed with the p"}, {"t": "(b)", "p": "/us/nsn/tmchippewa/council/code/14.05.010#(b)", "et": "para", "sc": "Section 14.05.010(b)", "x": "Exclusively from the income and revenues of certain designated projects whe"}, {"t": "(c)", "p": "/us/nsn/tmchippewa/council/code/14.05.010#(c)", "et": "para", "sc": "Section 14.05.010(c)", "x": "From its revenues generally. Any of such bonuses may be additionally secure"}]}, {"t": "14.05.020 Liability", "p": "/us/nsn/tmchippewa/council/code/14.05.020", "et": "section", "sc": "Section 14.05.020", "sp": "library|Turtle Mountain Band of Chippewa Indians Tribal Code|14|14.05|14.05.020", "c": [{"t": "(a)", "p": "/us/nsn/tmchippewa/council/code/14.05.020#(a)", "et": "para", "sc": "Section 14.05.020(a)", "x": "Neither the Commissioner of the Authority, nor any person executing the bon"}, {"t": "(b)", "p": "/us/nsn/tmchippewa/council/code/14.05.020#(b)", "et": "para", "sc": "Section 14.05.020(b)", "x": "The bonds and other obligations of the Authority shall not be a debt of the"}]}, {"t": "14.05.030 Tax", "p": "/us/nsn/tmchippewa/council/code/14.05.030", "et": "section", "sc": "Section 14.05.030", "sp": "library|Turtle Mountain Band of Chippewa Indians Tribal Code|14|14.05|14.05.030"}, {"t": "14.05.040 Sale Procedure", "p": "/us/nsn/tmchippewa/council/code/14.05.040", "et": "section", "sc": "Section 14.05.040", "sp": "library|Turtle Mountain Band of Chippewa Indians Tribal Code|14|14.05|14.05.040", "c": [{"t": "(a)", "p": "/us/nsn/tmchippewa/council/code/14.05.040#(a)", "et": "para", "sc": "Section 14.05.040(a)", "x": "Bonds of the Authority shall be authorized by a resolution adopted by the v"}, {"t": "(b)", "p": "/us/nsn/tmchippewa/council/code/14.05.040#(b)", "et": "para", "sc": "Section 14.05.040(b)", "x": "The bonds shall bear such dates, mature at such times, bear interest at suc"}, {"t": "(c)", "p": "/us/nsn/tmchippewa/council/code/14.05.040#(c)", "et": "para", "sc": "Section 14.05.040(c)", "x": "The bonds may be sold at public or private sale at not less than par."}, {"t": "(d)", "p": "/us/nsn/tmchippewa/council/code/14.05.040#(d)", "et": "para", "sc": "Section 14.05.040(d)", "x": "In case of any of the Commissioners of the Authority whose signatures appea"}]}, {"t": "14.05.050 Bonds of the Authority Shall Be Fully Negotiable", "p": "/us/nsn/tmchippewa/council/code/14.05.050", "et": "section", "sc": "Section 14.05.050", "sp": "library|Turtle Mountain Band of Chippewa Indians Tribal Code|14|14.05|14.05.050"}, {"t": "14.05.060 Administration of Bonds", "p": "/us/nsn/tmchippewa/council/code/14.05.060", "et": "section", "sc": "Section 14.05.060", "sp": "library|Turtle Mountain Band of Chippewa Indians Tribal Code|14|14.05|14.05.060", "c": [{"t": "(a)", "p": "/us/nsn/tmchippewa/council/code/14.05.060#(a)", "et": "para", "sc": "Section 14.05.060(a)", "x": "Pledge all or any part of its gross or net rents, fees or revenues to which"}, {"t": "(b)", "p": "/us/nsn/tmchippewa/council/code/14.05.060#(b)", "et": "para", "sc": "Section 14.05.060(b)", "x": "Provide for the powers and duties of obligee and limit their liabilities an"}, {"t": "(c)", "p": "/us/nsn/tmchippewa/council/code/14.05.060#(c)", "et": "para", "sc": "Section 14.05.060(c)", "x": "Covenant against pledging all or any part of its rents, fees and revenues o"}, {"t": "(d)", "p": "/us/nsn/tmchippewa/council/code/14.05.060#(d)", "et": "para", "sc": "Section 14.05.060(d)", "x": "Covenant with respect to limitations on its right to sell, lease or otherwi"}, {"t": "(e)", "p": "/us/nsn/tmchippewa/council/code/14.05.060#(e)", "et": "para", "sc": "Section 14.05.060(e)", "x": "Covenant as to what other or additional debts or obligations may be incurre"}, {"t": "(f)", "p": "/us/nsn/tmchippewa/council/code/14.05.060#(f)", "et": "para", "sc": "Section 14.05.060(f)", "x": "Covenant as to the bonds to be issued and as to the issuance of such bonds "}, {"t": "(g)", "p": "/us/nsn/tmchippewa/council/code/14.05.060#(g)", "et": "para", "sc": "Section 14.05.060(g)", "x": "Provide for the replacement of lost, destroyed or mutilated bonds."}, {"t": "(h)", "p": "/us/nsn/tmchippewa/council/code/14.05.060#(h)", "et": "para", "sc": "Section 14.05.060(h)", "x": "Covenant against extending the time for the payment of its bonds or interes"}, {"t": "(i)", "p": "/us/nsn/tmchippewa/council/code/14.05.060#(i)", "et": "para", "sc": "Section 14.05.060(i)", "x": "Redeem the bonds and covenant for their redemption and provide the terms an"}, {"t": "(j)", "p": "/us/nsn/tmchippewa/council/code/14.05.060#(j)", "et": "para", "sc": "Section 14.05.060(j)", "x": "Covenant covering the rents and fees to be charged in the operation of a pr"}, {"t": "(k)", "p": "/us/nsn/tmchippewa/council/code/14.05.060#(k)", "et": "para", "sc": "Section 14.05.060(k)", "x": "Create or authorize the creation of special funds by moneys held for constr"}, {"t": "(l)", "p": "/us/nsn/tmchippewa/council/code/14.05.060#(l)", "et": "para", "sc": "Section 14.05.060(l)", "x": "Prescribe the procedure, if any, by which the terms of any contract with bo"}, {"t": "(m)", "p": "/us/nsn/tmchippewa/council/code/14.05.060#(m)", "et": "para", "sc": "Section 14.05.060(m)", "x": "Covenant as to the use, maintenance and replacement of its real or personal"}, {"t": "(n)", "p": "/us/nsn/tmchippewa/council/code/14.05.060#(n)", "et": "para", "sc": "Section 14.05.060(n)", "x": "Covenant as to the rights, liabilities, powers and duties arising upon the "}, {"t": "(o)", "p": "/us/nsn/tmchippewa/council/code/14.05.060#(o)", "et": "para", "sc": "Section 14.05.060(o)", "x": "Covenant and prescribe as to events of default and terms and conditions upo"}, {"t": "(p)", "p": "/us/nsn/tmchippewa/council/code/14.05.060#(p)", "et": "para", "sc": "Section 14.05.060(p)", "x": "Vest in any obligee or any proportion of them the right to enforce the paym"}, {"t": "(q)", "p": "/us/nsn/tmchippewa/council/code/14.05.060#(q)", "et": "para", "sc": "Section 14.05.060(q)", "x": "Exercise all or any part or combination of the powers granted in this secti"}, {"t": "(r)", "p": "/us/nsn/tmchippewa/council/code/14.05.060#(r)", "et": "para", "sc": "Section 14.05.060(r)", "x": "Make covenants other than and in addition to the covenants expressly author"}, {"t": "(s)", "p": "/us/nsn/tmchippewa/council/code/14.05.060#(s)", "et": "para", "sc": "Section 14.05.060(s)", "x": "Make any covenants and do any acts and things necessary or convenient or de"}]}]}, {"t": "Chapter 14.06 Miscellaneous", "p": "/us/nsn/tmchippewa/council/code/14.06", "et": "container", "sc": "Chapter 14.06", "sp": "library|Turtle Mountain Band of Chippewa Indians Tribal Code|14|14.06", "c": [{"t": "14.06.010 Reports", "p": "/us/nsn/tmchippewa/council/code/14.06.010", "et": "section", "sc": "Section 14.06.010", "sp": "library|Turtle Mountain Band of Chippewa Indians Tribal Code|14|14.06|14.06.010", "c": [{"t": "(a)", "p": "/us/nsn/tmchippewa/council/code/14.06.010#(a)", "et": "para", "sc": "Section 14.06.010(a)", "x": "The names of occupants of all the housing units;"}, {"t": "(b)", "p": "/us/nsn/tmchippewa/council/code/14.06.010#(b)", "et": "para", "sc": "Section 14.06.010(b)", "x": "The number of vacancies, if any;"}, {"t": "(c)", "p": "/us/nsn/tmchippewa/council/code/14.06.010#(c)", "et": "para", "sc": "Section 14.06.010(c)", "x": "The status of construction, maintenance and repair of all housing units;"}, {"t": "(d)", "p": "/us/nsn/tmchippewa/council/code/14.06.010#(d)", "et": "para", "sc": "Section 14.06.010(d)", "x": "Any significant problems and accomplishments;"}, {"t": "(e)", "p": "/us/nsn/tmchippewa/council/code/14.06.010#(e)", "et": "para", "sc": "Section 14.06.010(e)", "x": "Plans for the future; and"}, {"t": "(f)", "p": "/us/nsn/tmchippewa/council/code/14.06.010#(f)", "et": "para", "sc": "Section 14.06.010(f)", "x": "Such other information as the Authority or the"}]}, {"t": "14.06.020 Conflict of Interests", "p": "/us/nsn/tmchippewa/council/code/14.06.020", "et": "section", "sc": "Section 14.06.020", "sp": "library|Turtle Mountain Band of Chippewa Indians Tribal Code|14|14.06|14.06.020"}, {"t": "14.06.030 Construction Codes", "p": "/us/nsn/tmchippewa/council/code/14.06.030", "et": "section", "sc": "Section 14.06.030", "sp": "library|Turtle Mountain Band of Chippewa Indians Tribal Code|14|14.06|14.06.030"}, {"t": "14.06.040 Liens or Judgments", "p": "/us/nsn/tmchippewa/council/code/14.06.040", "et": "section", "sc": "Section 14.06.040", "sp": "library|Turtle Mountain Band of Chippewa Indians Tribal Code|14|14.06|14.06.040"}, {"t": "14.06.050 Fidelity Bond", "p": "/us/nsn/tmchippewa/council/code/14.06.050", "et": "section", "sc": "Section 14.06.050", "sp": "library|Turtle Mountain Band of Chippewa Indians Tribal Code|14|14.06|14.06.050"}]}, {"t": "Chapter 14.07 Cooperation in Connection with Projects", "p": "/us/nsn/tmchippewa/council/code/14.07", "et": "container", "sc": "Chapter 14.07", "sp": "library|Turtle Mountain Band of Chippewa Indians Tribal Code|14|14.07", "c": [{"t": "14.07.010 Cooperation in Connection with Projects", "p": "/us/nsn/tmchippewa/council/code/14.07.010", "et": "section", "sc": "Section 14.07.010", "sp": "library|Turtle Mountain Band of Chippewa Indians Tribal Code|14|14.07|14.07.010", "c": [{"t": "(a)", "p": "/us/nsn/tmchippewa/council/code/14.07.010#(a)", "et": "para", "sc": "Section 14.07.010(a)", "x": "It will not levy, or impose any real or personal property taxes or special "}, {"t": "(b)", "p": "/us/nsn/tmchippewa/council/code/14.07.010#(b)", "et": "para", "sc": "Section 14.07.010(b)", "x": "It will furnish or cause to be furnished to the Authority and the tenants o"}, {"t": "(c)", "p": "/us/nsn/tmchippewa/council/code/14.07.010#(c)", "et": "para", "sc": "Section 14.07.010(c)", "x": "Insofar as it may lawfully do so, it will grant such deviations from any pr"}, {"t": "(d)", "p": "/us/nsn/tmchippewa/council/code/14.07.010#(d)", "et": "para", "sc": "Section 14.07.010(d)", "x": "It will join in any disposition of project property or interest therein by "}]}, {"t": "14.07.020 Sovereign Immunity", "p": "/us/nsn/tmchippewa/council/code/14.07.020", "et": "section", "sc": "Section 14.07.020", "sp": "library|Turtle Mountain Band of Chippewa Indians Tribal Code|14|14.07|14.07.020"}]}, {"t": "Chapter 14.08 Approval by Secretary of the Interior", "p": "/us/nsn/tmchippewa/council/code/14.08", "et": "container", "sc": "Chapter 14.08", "sp": "library|Turtle Mountain Band of Chippewa Indians Tribal Code|14|14.08", "c": [{"t": "14.08.010 Financial Assistance", "p": "/us/nsn/tmchippewa/council/code/14.08.010", "et": "section", "sc": "Section 14.08.010", "sp": "library|Turtle Mountain Band of Chippewa Indians Tribal Code|14|14.08|14.08.010"}]}]}