{"t": "Title 46 Infrastructure Ordinance", "p": "/us/nsn/tmchippewa/council/code/46", "et": "container", "dj": "/us/nsn/tmchippewa/council/code/index.json", "fh": "/us/nsn/tmchippewa/council/code/46/index.full.html", "sc": "Title 46", "sp": "library|Turtle Mountain Band of Chippewa Indians Tribal Code|46", "c": [{"t": "Chapter 46.01 Consultation Process", "p": "/us/nsn/tmchippewa/council/code/46.01", "et": "container", "sc": "Chapter 46.01", "sp": "library|Turtle Mountain Band of Chippewa Indians Tribal Code|46|46.01", "c": [{"t": "46.0101 Establishment of Consultation Process", "p": "/us/nsn/tmchippewa/council/code/46.0101", "et": "section", "sc": "Section 46.0101", "sp": "library|Turtle Mountain Band of Chippewa Indians Tribal Code|46|46.01|46.0101"}, {"t": "46.0102 Tribal Council Establishment of Infrastructure", "p": "/us/nsn/tmchippewa/council/code/46.0102", "et": "section", "sc": "Section 46.0102", "sp": "library|Turtle Mountain Band of Chippewa Indians Tribal Code|46|46.01|46.0102"}, {"t": "46.0103 Purpose", "p": "/us/nsn/tmchippewa/council/code/46.0103", "et": "section", "sc": "Section 46.0103", "sp": "library|Turtle Mountain Band of Chippewa Indians Tribal Code|46|46.01|46.0103"}, {"t": "46.0104 Title of Consultation Process", "p": "/us/nsn/tmchippewa/council/code/46.0104", "et": "section", "sc": "Section 46.0104", "sp": "library|Turtle Mountain Band of Chippewa Indians Tribal Code|46|46.01|46.0104"}, {"t": "46.0105 Definition of Terms", "p": "/us/nsn/tmchippewa/council/code/46.0105", "et": "section", "sc": "Section 46.0105", "sp": "library|Turtle Mountain Band of Chippewa Indians Tribal Code|46|46.01|46.0105", "c": [{"t": "(1)", "p": "/us/nsn/tmchippewa/council/code/46.0105#(1)", "et": "para", "sc": "Section 46.0105(1)", "x": "\"Business License\" mean a license issued pursuant to the Turtle Mountain Ba"}, {"t": "(2)", "p": "/us/nsn/tmchippewa/council/code/46.0105#(2)", "et": "para", "sc": "Section 46.0105(2)", "x": "\"Cease and Desist Order\" means an Order issued by the Tribal Court to a Per"}, {"t": "(3)", "p": "/us/nsn/tmchippewa/council/code/46.0105#(3)", "et": "para", "sc": "Section 46.0105(3)", "x": "\"Construction\" means any activity that is directly related to building or r"}, {"t": "(4)", "p": "/us/nsn/tmchippewa/council/code/46.0105#(4)", "et": "para", "sc": "Section 46.0105(4)", "x": "\"Construction PermiT\" means the final Permit issued by the Tribal Council a"}, {"t": "(5)", "p": "/us/nsn/tmchippewa/council/code/46.0105#(5)", "et": "para", "sc": "Section 46.0105(5)", "x": "\"Declaration\" means a formal response from any Infrastructure Department Di"}, {"t": "(6)", "p": "/us/nsn/tmchippewa/council/code/46.0105#(6)", "et": "para", "sc": "Section 46.0105(6)", "x": "\"Design Permit\" means the approval issued by the Tribal Council to a Person"}, {"t": "(7)", "p": "/us/nsn/tmchippewa/council/code/46.0105#(7)", "et": "para", "sc": "Section 46.0105(7)", "x": "\"Designated Director(s)\" means any Tribal department director of a Departme"}, {"t": "(8)", "p": "/us/nsn/tmchippewa/council/code/46.0105#(8)", "et": "para", "sc": "Section 46.0105(8)", "x": "\"Employee\" means any person that is employed by the Turtle Mountain Band of"}, {"t": "(9)", "p": "/us/nsn/tmchippewa/council/code/46.0105#(9)", "et": "para", "sc": "Section 46.0105(9)", "x": "\"Exterior Boundaries of the Turtle Mountain Band of Chippewa Indian Reserva"}, {"t": "(10)", "p": "/us/nsn/tmchippewa/council/code/46.0105#(10)", "et": "para", "sc": "Section 46.0105(10)", "x": "\"External Organization\" means any organization, agency or governmental enti"}, {"t": "(11)", "p": "/us/nsn/tmchippewa/council/code/46.0105#(11)", "et": "para", "sc": "Section 46.0105(11)", "x": "\"Federal Acquisition Requirements\" means the governing law when dealing wit"}, {"t": "(12)", "p": "/us/nsn/tmchippewa/council/code/46.0105#(12)", "et": "para", "sc": "Section 46.0105(12)", "c": [{"t": "(a)", "p": "/us/nsn/tmchippewa/council/code/46.0105#(12)(a)", "et": "para", "sc": "Section 46.0105(12)(a)", "x": "Environmental Protection;"}, {"t": "(b)", "p": "/us/nsn/tmchippewa/council/code/46.0105#(12)(b)", "et": "para", "sc": "Section 46.0105(12)(b)", "x": "Housing;"}, {"t": "(c)", "p": "/us/nsn/tmchippewa/council/code/46.0105#(12)(c)", "et": "para", "sc": "Section 46.0105(12)(c)", "x": "Land Realty;"}, {"t": "(d)", "p": "/us/nsn/tmchippewa/council/code/46.0105#(12)(d)", "et": "para", "sc": "Section 46.0105(12)(d)", "x": "Public Utilities."}, {"t": "(e)", "p": "/us/nsn/tmchippewa/council/code/46.0105#(12)(e)", "et": "para", "sc": "Section 46.0105(12)(e)", "x": "Transportation;"}, {"t": "(f)", "p": "/us/nsn/tmchippewa/council/code/46.0105#(12)(f)", "et": "para", "sc": "Section 46.0105(12)(f)", "x": "Tribal Employment Rights Office;"}, {"t": "(g)", "p": "/us/nsn/tmchippewa/council/code/46.0105#(12)(g)", "et": "para", "sc": "Section 46.0105(12)(g)", "x": "Water Resources."}], "x": "\"Infrastructure Department\" herein means any department employed or utilize"}, {"t": "(13)", "p": "/us/nsn/tmchippewa/council/code/46.0105#(13)", "et": "para", "sc": "Section 46.0105(13)", "x": "\"Internal Organization\" means any Tribal department or program listed under"}, {"t": "(14)", "p": "/us/nsn/tmchippewa/council/code/46.0105#(14)", "et": "para", "sc": "Section 46.0105(14)", "x": "\"Notification\" means a formal invitation to Infrastructure Departments to p"}, {"t": "(15)", "p": "/us/nsn/tmchippewa/council/code/46.0105#(15)", "et": "para", "sc": "Section 46.0105(15)", "x": "\"Permit\" refers to the authorization issued by the Tribal Council to a Pers"}, {"t": "(16)", "p": "/us/nsn/tmchippewa/council/code/46.0105#(16)", "et": "para", "sc": "Section 46.0105(16)", "x": "\"Permit Application\" means the written form and associated documents provid"}, {"t": "(17)", "p": "/us/nsn/tmchippewa/council/code/46.0105#(17)", "et": "para", "sc": "Section 46.0105(17)", "x": "\"Person\" means a natural person, a tribal employee, any business partnershi"}, {"t": "(18)", "p": "/us/nsn/tmchippewa/council/code/46.0105#(18)", "et": "para", "sc": "Section 46.0105(18)", "x": "\"Project\" means a Structure located on the Turtle Mountain Reservation, or "}, {"t": "(19)", "p": "/us/nsn/tmchippewa/council/code/46.0105#(19)", "et": "para", "sc": "Section 46.0105(19)", "x": "\"Right of Way\" means the right to access a strip of land, measured in feet,"}, {"t": "(20)", "p": "/us/nsn/tmchippewa/council/code/46.0105#(20)", "et": "para", "sc": "Section 46.0105(20)", "x": "\"Structure\" means a permanent or temporary building, or any piece of work, "}, {"t": "(21)", "p": "/us/nsn/tmchippewa/council/code/46.0105#(21)", "et": "para", "sc": "Section 46.0105(21)", "x": "\"Tribal Court\" means the Tribal Court of the Turtle Mountain Band of Chippe"}, {"t": "(22)", "p": "/us/nsn/tmchippewa/council/code/46.0105#(22)", "et": "para", "sc": "Section 46.0105(22)", "x": "\"Turtle Mountain Band of Chippewa Indian Reservation\" means all areas encom"}, {"t": "(23)", "p": "/us/nsn/tmchippewa/council/code/46.0105#(23)", "et": "para", "sc": "Section 46.0105(23)", "x": "\"Waiver\" means that a Tribal Infrastructure Departments declaration that it"}]}, {"t": "46.0106 Tribal Involvement in Infrastructure Development", "p": "/us/nsn/tmchippewa/council/code/46.0106", "et": "section", "sc": "Section 46.0106", "sp": "library|Turtle Mountain Band of Chippewa Indians Tribal Code|46|46.01|46.0106", "c": [{"t": "(1)", "p": "/us/nsn/tmchippewa/council/code/46.0106#(1)", "et": "para", "sc": "Section 46.0106(1)", "x": "Shall be enforced with the understanding that the Turtle Mountain Tribal Co"}, {"t": "(2)", "p": "/us/nsn/tmchippewa/council/code/46.0106#(2)", "et": "para", "sc": "Section 46.0106(2)", "x": "Tribal Involvement with Infrastructure Development shall include, but is no"}, {"t": "(3)", "p": "/us/nsn/tmchippewa/council/code/46.0106#(3)", "et": "para", "sc": "Section 46.0106(3)", "x": "No Person within the Exterior Boundaries of the Turtle Mountain Indian Rese"}, {"t": "(4)", "p": "/us/nsn/tmchippewa/council/code/46.0106#(4)", "et": "para", "sc": "Section 46.0106(4)", "x": "No employee within the Exterior Boundaries or subject to the TMBC Employee "}]}, {"t": "46.0107 Designated Directors Shall Serve as Local Experts", "p": "/us/nsn/tmchippewa/council/code/46.0107", "et": "section", "sc": "Section 46.0107", "sp": "library|Turtle Mountain Band of Chippewa Indians Tribal Code|46|46.01|46.0107", "c": [{"t": "(1)", "p": "/us/nsn/tmchippewa/council/code/46.0107#(1)", "et": "para", "sc": "Section 46.0107(1)", "x": "Designated Directors shall serve as local experts when dealing with planned"}, {"t": "(2)", "p": "/us/nsn/tmchippewa/council/code/46.0107#(2)", "et": "para", "sc": "Section 46.0107(2)", "x": "Any Person and/or Employee planning on performing a Project within the Exte"}, {"t": "(3)", "p": "/us/nsn/tmchippewa/council/code/46.0107#(3)", "et": "para", "sc": "Section 46.0107(3)", "x": "The Designated Directors shall be involved in Project plans at 0% complete;"}]}, {"t": "46.0108 Designated Directors Shall Declare a Projects Impact", "p": "/us/nsn/tmchippewa/council/code/46.0108", "et": "section", "sc": "Section 46.0108", "sp": "library|Turtle Mountain Band of Chippewa Indians Tribal Code|46|46.01|46.0108", "c": [{"t": "(1)", "p": "/us/nsn/tmchippewa/council/code/46.0108#(1)", "et": "para", "sc": "Section 46.0108(1)", "x": "Designated Director's shall have the responsibility to declare that a Proje"}, {"t": "(2)", "p": "/us/nsn/tmchippewa/council/code/46.0108#(2)", "et": "para", "sc": "Section 46.0108(2)", "x": "Not all Designated Directors will need to be involved in Project reviews.  "}, {"t": "(3)", "p": "/us/nsn/tmchippewa/council/code/46.0108#(3)", "et": "para", "sc": "Section 46.0108(3)", "x": "Designated Directors will have the responsibility to declare in writing tha"}]}, {"t": "46.0109 Designated Director's Duties", "p": "/us/nsn/tmchippewa/council/code/46.0109", "et": "section", "sc": "Section 46.0109", "sp": "library|Turtle Mountain Band of Chippewa Indians Tribal Code|46|46.01|46.0109", "c": [{"t": "(1)", "p": "/us/nsn/tmchippewa/council/code/46.0109#(1)", "et": "para", "sc": "Section 46.0109(1)", "x": "Declaring the interest of their Infrastructure Department to be involved in"}, {"t": "(2)", "p": "/us/nsn/tmchippewa/council/code/46.0109#(2)", "et": "para", "sc": "Section 46.0109(2)", "x": "Documenting findings and making recommendations to the Turtle Mountain Band"}, {"t": "(3)", "p": "/us/nsn/tmchippewa/council/code/46.0109#(3)", "et": "para", "sc": "Section 46.0109(3)", "x": "Identifying impacts to the Tribe's infrastructure systems (utilities, water"}, {"t": "(4)", "p": "/us/nsn/tmchippewa/council/code/46.0109#(4)", "et": "para", "sc": "Section 46.0109(4)", "x": "Reviewing and providing comments and recommendations to the Tribal Council "}, {"t": "(5)", "p": "/us/nsn/tmchippewa/council/code/46.0109#(5)", "et": "para", "sc": "Section 46.0109(5)", "x": "Examining design plans to determine whether such plans meet or exceed minim"}, {"t": "(6)", "p": "/us/nsn/tmchippewa/council/code/46.0109#(6)", "et": "para", "sc": "Section 46.0109(6)", "x": "Managing the existing and future infrastructure components on the Exterior "}, {"t": "(7)", "p": "/us/nsn/tmchippewa/council/code/46.0109#(7)", "et": "para", "sc": "Section 46.0109(7)", "x": "Assisting with the enforcement of penalties against violators."}, {"t": "(8)", "p": "/us/nsn/tmchippewa/council/code/46.0109#(8)", "et": "para", "sc": "Section 46.0109(8)", "x": "Disseminating this Ordinance to all Persons and Employees who work \twith or"}]}, {"t": "46.0110 Persons with Permit Forms", "p": "/us/nsn/tmchippewa/council/code/46.0110", "et": "section", "sc": "Section 46.0110", "sp": "library|Turtle Mountain Band of Chippewa Indians Tribal Code|46|46.01|46.0110", "c": [{"t": "(1)", "p": "/us/nsn/tmchippewa/council/code/46.0110#(1)", "et": "para", "sc": "Section 46.0110(1)", "x": "Any Person, by his signature upon said Permit, agrees that a consensual bus"}, {"t": "(2)", "p": "/us/nsn/tmchippewa/council/code/46.0110#(2)", "et": "para", "sc": "Section 46.0110(2)", "x": "Any Person, by his signature upon said Permit, expressly agrees that a Perm"}, {"t": "(3)", "p": "/us/nsn/tmchippewa/council/code/46.0110#(3)", "et": "para", "sc": "Section 46.0110(3)", "x": "Any Person, by his signature upon said Permit, expressly agrees that failur"}]}, {"t": "46.0111 Consensual Process Must Be Established", "p": "/us/nsn/tmchippewa/council/code/46.0111", "et": "section", "sc": "Section 46.0111", "sp": "library|Turtle Mountain Band of Chippewa Indians Tribal Code|46|46.01|46.0111", "c": [{"t": "(1)", "p": "/us/nsn/tmchippewa/council/code/46.0111#(1)", "et": "para", "sc": "Section 46.0111(1)", "x": "Any Person employed by the Turtle Mountain Band of Chippewa agrees that a c"}, {"t": "(2)", "p": "/us/nsn/tmchippewa/council/code/46.0111#(2)", "et": "para", "sc": "Section 46.0111(2)", "x": "Any Person employed by the Turtle Mountain Band of Chippewa expressly agree"}, {"t": "(3)", "p": "/us/nsn/tmchippewa/council/code/46.0111#(3)", "et": "para", "sc": "Section 46.0111(3)", "x": "Any Person employed by the Turtle Mountain Band of Chippewa expressly agree"}]}, {"t": "46.0112 Filing Electronic Monthly Reports", "p": "/us/nsn/tmchippewa/council/code/46.0112", "et": "section", "sc": "Section 46.0112", "sp": "library|Turtle Mountain Band of Chippewa Indians Tribal Code|46|46.01|46.0112"}, {"t": "46.0113 Electronic Reports Due on or Before the 20Th Day of the Calendar Month", "p": "/us/nsn/tmchippewa/council/code/46.0113", "et": "section", "sc": "Section 46.0113", "sp": "library|Turtle Mountain Band of Chippewa Indians Tribal Code|46|46.01|46.0113"}, {"t": "46.0114 Statement of Work Completed and Remaining", "p": "/us/nsn/tmchippewa/council/code/46.0114", "et": "section", "sc": "Section 46.0114", "sp": "library|Turtle Mountain Band of Chippewa Indians Tribal Code|46|46.01|46.0114"}, {"t": "46.0115 Failure to Comply", "p": "/us/nsn/tmchippewa/council/code/46.0115", "et": "section", "sc": "Section 46.0115", "sp": "library|Turtle Mountain Band of Chippewa Indians Tribal Code|46|46.01|46.0115", "c": [{"t": "(1)", "p": "/us/nsn/tmchippewa/council/code/46.0115#(1)", "et": "para", "sc": "Section 46.0115(1)", "x": "Persons shall be subject to fees or interest charges which the Tribe may ca"}, {"t": "(2)", "p": "/us/nsn/tmchippewa/council/code/46.0115#(2)", "et": "para", "sc": "Section 46.0115(2)", "x": "Employees shall be subject to insubordination and disciplinary actions and "}]}, {"t": "46.0116 Penalties and Interest", "p": "/us/nsn/tmchippewa/council/code/46.0116", "et": "section", "sc": "Section 46.0116", "sp": "library|Turtle Mountain Band of Chippewa Indians Tribal Code|46|46.01|46.0116", "c": [{"t": "(1)", "p": "/us/nsn/tmchippewa/council/code/46.0116#(1)", "et": "para", "sc": "Section 46.0116(1)", "x": "Any of the Turtle Mountain Band of Chippewa Designated Director(s) are auth"}, {"t": "(2)", "p": "/us/nsn/tmchippewa/council/code/46.0116#(2)", "et": "para", "sc": "Section 46.0116(2)", "x": "Any of the Turtle Mountain Band of Chippewa Designated Director(s) are auth"}]}, {"t": "46.0117 To Issue Preliminary Injunction", "p": "/us/nsn/tmchippewa/council/code/46.0117", "et": "section", "sc": "Section 46.0117", "sp": "library|Turtle Mountain Band of Chippewa Indians Tribal Code|46|46.01|46.0117"}, {"t": "46.0118 Failure to Comply with This Ordinance", "p": "/us/nsn/tmchippewa/council/code/46.0118", "et": "section", "sc": "Section 46.0118", "sp": "library|Turtle Mountain Band of Chippewa Indians Tribal Code|46|46.01|46.0118", "c": [{"t": "(1)", "p": "/us/nsn/tmchippewa/council/code/46.0118#(1)", "et": "para", "sc": "Section 46.0118(1)", "x": "A Person or Employee shall not knowingly commence any planning where any of"}, {"t": "(2)", "p": "/us/nsn/tmchippewa/council/code/46.0118#(2)", "et": "para", "sc": "Section 46.0118(2)", "x": "A Person or Employee who shall fail to comply with this Ordinance shall be "}, {"t": "(3)", "p": "/us/nsn/tmchippewa/council/code/46.0118#(3)", "et": "para", "sc": "Section 46.0118(3)", "x": "Failure by any Person to secure a Business License and/or Permit from the T"}]}, {"t": "46.0119 Officers Authorized and Mandated to Enforce Sanctions", "p": "/us/nsn/tmchippewa/council/code/46.0119", "et": "section", "sc": "Section 46.0119", "sp": "library|Turtle Mountain Band of Chippewa Indians Tribal Code|46|46.01|46.0119", "c": [{"t": "(1)", "p": "/us/nsn/tmchippewa/council/code/46.0119#(1)", "et": "para", "sc": "Section 46.0119(1)", "x": "Officers of the Turtle Mountain Band of Chippewa are authorized and mandate"}, {"t": "(2)", "p": "/us/nsn/tmchippewa/council/code/46.0119#(2)", "et": "para", "sc": "Section 46.0119(2)", "x": "If, after inquiries are made, the Person is found to be in violation of Tri"}, {"t": "(3)", "p": "/us/nsn/tmchippewa/council/code/46.0119#(3)", "et": "para", "sc": "Section 46.0119(3)", "x": "The Designated Director(s) of the Turtle Mountain Band of Chippewa are auth"}]}, {"t": "46.0120 Prior Inconsistent Ordinances Hereby Repealed", "p": "/us/nsn/tmchippewa/council/code/46.0120", "et": "section", "sc": "Section 46.0120", "sp": "library|Turtle Mountain Band of Chippewa Indians Tribal Code|46|46.01|46.0120"}, {"t": "46.0121 Invalid or Not Enforceable as a Matter of Law", "p": "/us/nsn/tmchippewa/council/code/46.0121", "et": "section", "sc": "Section 46.0121", "sp": "library|Turtle Mountain Band of Chippewa Indians Tribal Code|46|46.01|46.0121"}, {"t": "46.0122 Sovereign Immunity", "p": "/us/nsn/tmchippewa/council/code/46.0122", "et": "section", "sc": "Section 46.0122", "sp": "library|Turtle Mountain Band of Chippewa Indians Tribal Code|46|46.01|46.0122"}]}]}